{
  "backgroundType": "gradient",
  "plainBackgroundMode": "daylight",
  "gradientColors": "#EE7752, #E73C7E, #23A6D5, #23D5AB",
  "FirstName": "Akshat",
  "MiddleName": "",
  "LastName": "Jindal",
  "devDesc": " | Engineer | Programmer | Maker | Designer | Developer ",
  "icons": [
    {
      "id": 0,
      "image": "fa-github",
      "url": "https://github.com/AkshatJindal1",
      "style": "socialicons"
    },
    {
      "id": 1,
      "image": "fa-instagram",
      "url": "https://www.instagram.com/_trippy_lens/",
      "style": "socialicons"
    },
    {
      "id": 2,
      "image": "fa-linkedin",
      "url": "https://www.  linkedin.com/in/akshat-jindal07/",
      "style": "socialicons"
    }
  ],
  "aboutHeading": "About Me",
  "showInstaProfilePic": true,
  "instaLink": "https://www.instagram.com/",
  "instaUsername": "_trippy_lens",
  "instaQuerry": "/?__a=1",
  "profilePic": "../../editable-stuff/akshat.jpg",
  "imgSize": 375,
  "aboutDescription": "Hello! My name is Akshat Jindal, and I am a graduate from Indian Institute of Technology, Kharagpur, India. Currently I am working as a full stack developer at Publicis Sapient. I'm most passionate about giving back to the community, and my goal is to pursue this passion within the field of software engineering!",
  "projectHeading": "Recent Projects",
  "gitHubLink": "https://api.github.com/",
  "gitHubUsername": "AkshatJindal1",
  "gitHubQuery": "/repos?sort=updated&direction=desc",
  "projectsLength": 0,
  "specificRepos": ["AkshatJindal1.github.io", "car-damage-detector", "NLP-with-tensorflow", "JwtAuthenticationDemo"],
  "mediaHeading": "Featured Media",
  "contactHeading": "Contact Me",
  "contactDescription": "Have a question? Need a tip? Feel free to reach out to me or send an email ",
  "showNavigationbar": true,
  "showBlog": true,

  "skills" : {
    "show": true,
    "heading": "Skills",
    "hardSkills": [
      { "name": "Java", "value": 90 },
      { "name": "Python", "value": 75 },
      { "name": "Data Structures", "value": 85 },
      { "name": "C/C++", "value": 65 },
      { "name": "JavaScript", "value": 80 },
      { "name": "Springboot", "value": 85},
      { "name": "React", "value": 65 },
      { "name": "Scala", "value": 60},
      { "name": "MongoDB", "value": 70},
      { "name": "AWS", "value": 70}
    ],
    "softSkills": [
      { "name": "Goal-Oriented", "value": 80 },
      { "name": "Collaboration", "value": 90 },
      { "name": "Positivity", "value": 75 },
      { "name": "Adaptability", "value": 85 },
      { "name": "Problem Solving", "value": 75 },
      { "name": "Empathy", "value": 90 },
      { "name": "Organization", "value": 70 },
      { "name": "Creativity", "value": 90 }
    ]
  },

  "leadership": {
    "heading": "Leadership"
  }
}
